bslz4_to_sparse/__init__.py
bslz4_to_sparse/bslz4_to_sparse.cp314-win_amd64.pyd
bslz4_to_sparse-0.0.16.dist-info/licenses/LICENSE
bslz4_to_sparse-0.0.16.dist-info/METADATA
bslz4_to_sparse-0.0.16.dist-info/WHEEL
bslz4_to_sparse-0.0.16.dist-info/top_level.txt
bslz4_to_sparse-0.0.16.dist-info/RECORD
