Metadata-Version: 2.4
Name: bslz4_to_sparse
Version: 0.0.16
Home-page: http://github.com/jonwright/bslz4_to_sparse
Author: Jon Wright
Author-email: wright@esrf.fr
License: MIT
License-File: LICENSE
Requires-Dist: numpy
Requires-Dist: h5py
Dynamic: author
Dynamic: author-email
Dynamic: description
Dynamic: description-content-type
Dynamic: home-page
Dynamic: license
Dynamic: license-file
Dynamic: requires-dist
